rar/__init__.py
rar/metrics.py
rar/utils.py
rar/encoders/__init__.py
rar/encoders/huggingface_encoder.py
rar/encoders/simcse_encoder.py
rar/encoders/specter_encoder.py
rar/retrievers/__init__.py
rar/retrievers/bm25_retriever.py
rar/retrievers/dense_retriever.py
rar/retrievers/query2doc_bm25_retriever.py
rar/retrievers/query2doc_dense_retriever.py
rar/retrievers/utils.py
referral_augment-0.1.1.dist-info/LICENSE
referral_augment-0.1.1.dist-info/METADATA
referral_augment-0.1.1.dist-info/WHEEL
referral_augment-0.1.1.dist-info/top_level.txt
referral_augment-0.1.1.dist-info/RECORD
