Metadata-Version: 2.1
Name: referral-augment
Version: 0.1.1
Summary: Official implementation of "Referral Augmentation for Zero-Shot Information Retrieval"
Author-email: Michael Tang <mwtang@princeton.edu>
License: MIT License
Project-URL: Homepage, https://github.com/michaelwilliamtang/referral-augment
Keywords: retrieval
Classifier: License :: OSI Approved :: MIT License
Classifier: Programming Language :: Python :: 3
Classifier: Programming Language :: Python :: 3.7
Classifier: Programming Language :: Python :: 3.8
Classifier: Programming Language :: Python :: 3.9
Classifier: Programming Language :: Python :: 3.10
Classifier: Programming Language :: Python :: 3.11
Classifier: Intended Audience :: Science/Research
Classifier: Topic :: Scientific/Engineering :: Artificial Intelligence
Requires-Python: >=3.7
License-File: LICENSE
Requires-Dist: numpy
Requires-Dist: rank-bm25
Requires-Dist: sentence-transformers
Requires-Dist: sqlitedict
Requires-Dist: tokenizers
Requires-Dist: torch
Requires-Dist: torchvision
Requires-Dist: tqdm
Requires-Dist: transformers
